{
 "bad":false,
 "conda-forge.yml":{
  "provider":{
   "linux":"azure",
   "osx":"azure",
   "win":"azure"
  }
 },
 "feedstock_name":"amostra",
 "hash_type":"sha256",
 "linux_64_meta_yaml":{
  "about":{
   "home":"https://nsls-ii.github.io/amostra",
   "license":"BSD 3-Clause",
   "license_file":"LICENSE",
   "summary":"amostra is a collection of light-weight sample management classes"
  },
  "build":{
   "noarch":"python",
   "number":"1",
   "script":" -m pip install . --no-deps -vv"
  },
  "package":{
   "name":"amostra",
   "version":"1.0.0"
  },
  "requirements":{
   "host":[
    "python",
    "pip"
   ],
   "run":[
    "python",
    "doct",
    "jsonschema",
    "mongoquery",
    "pymongo",
    "pyyaml",
    "requests",
    "tornado",
    "ujson"
   ]
  },
  "source":{
   "sha256":"52a34cf993ddc1367832f263b417eb4ed4f88214792acf86a4bd98c6cd5c3173",
   "url":"https://github.com/NSLS-II/amostra/archive/v1.0.0.tar.gz"
  },
  "test":{
   "imports":[
    "amostra",
    "amostra.client",
    "amostra.sample_data",
    "amostra.server",
    "amostra.test"
   ]
  }
 },
 "linux_64_requirements":{
  "build":{
   "__set__":true,
   "elements":[]
  },
  "host":{
   "__set__":true,
   "elements":[
    "pip",
    "python"
   ]
  },
  "run":{
   "__set__":true,
   "elements":[
    "doct",
    "jsonschema",
    "mongoquery",
    "pymongo",
    "python",
    "pyyaml",
    "requests",
    "tornado",
    "ujson"
   ]
  },
  "test":{
   "__set__":true,
   "elements":[]
  }
 },
 "meta_yaml":{
  "about":{
   "home":"https://nsls-ii.github.io/amostra",
   "license":"BSD 3-Clause",
   "license_file":"LICENSE",
   "summary":"amostra is a collection of light-weight sample management classes"
  },
  "build":{
   "noarch":"python",
   "number":"1",
   "script":" -m pip install . --no-deps -vv"
  },
  "package":{
   "name":"amostra",
   "version":"1.0.0"
  },
  "requirements":{
   "host":[
    "python",
    "pip",
    "python",
    "pip",
    "python",
    "pip"
   ],
   "run":[
    "python",
    "doct",
    "jsonschema",
    "mongoquery",
    "pymongo",
    "pyyaml",
    "requests",
    "tornado",
    "ujson",
    "python",
    "doct",
    "jsonschema",
    "mongoquery",
    "pymongo",
    "pyyaml",
    "requests",
    "tornado",
    "ujson",
    "python",
    "doct",
    "jsonschema",
    "mongoquery",
    "pymongo",
    "pyyaml",
    "requests",
    "tornado",
    "ujson"
   ]
  },
  "source":{
   "sha256":"52a34cf993ddc1367832f263b417eb4ed4f88214792acf86a4bd98c6cd5c3173",
   "url":"https://github.com/NSLS-II/amostra/archive/v1.0.0.tar.gz"
  },
  "test":{
   "imports":[
    "amostra",
    "amostra.client",
    "amostra.sample_data",
    "amostra.server",
    "amostra.test",
    "amostra",
    "amostra.client",
    "amostra.sample_data",
    "amostra.server",
    "amostra.test",
    "amostra",
    "amostra.client",
    "amostra.sample_data",
    "amostra.server",
    "amostra.test"
   ]
  }
 },
 "name":"amostra",
 "osx_64_meta_yaml":{
  "about":{
   "home":"https://nsls-ii.github.io/amostra",
   "license":"BSD 3-Clause",
   "license_file":"LICENSE",
   "summary":"amostra is a collection of light-weight sample management classes"
  },
  "build":{
   "noarch":"python",
   "number":"1",
   "script":" -m pip install . --no-deps -vv"
  },
  "package":{
   "name":"amostra",
   "version":"1.0.0"
  },
  "requirements":{
   "host":[
    "python",
    "pip"
   ],
   "run":[
    "python",
    "doct",
    "jsonschema",
    "mongoquery",
    "pymongo",
    "pyyaml",
    "requests",
    "tornado",
    "ujson"
   ]
  },
  "source":{
   "sha256":"52a34cf993ddc1367832f263b417eb4ed4f88214792acf86a4bd98c6cd5c3173",
   "url":"https://github.com/NSLS-II/amostra/archive/v1.0.0.tar.gz"
  },
  "test":{
   "imports":[
    "amostra",
    "amostra.client",
    "amostra.sample_data",
    "amostra.server",
    "amostra.test"
   ]
  }
 },
 "osx_64_requirements":{
  "build":{
   "__set__":true,
   "elements":[]
  },
  "host":{
   "__set__":true,
   "elements":[
    "pip",
    "python"
   ]
  },
  "run":{
   "__set__":true,
   "elements":[
    "doct",
    "jsonschema",
    "mongoquery",
    "pymongo",
    "python",
    "pyyaml",
    "requests",
    "tornado",
    "ujson"
   ]
  },
  "test":{
   "__set__":true,
   "elements":[]
  }
 },
 "raw_meta_yaml":"{% set name = \"amostra\" %}\n{% set version = \"1.0.0\" %}\n{% set sha256 = \"52a34cf993ddc1367832f263b417eb4ed4f88214792acf86a4bd98c6cd5c3173\" %}\n\npackage:\n  name: {{ name }}\n  version: {{ version }}\n\nsource:\n  url: https://github.com/NSLS-II/{{ name  }}/archive/v{{ version }}.tar.gz\n  sha256: {{ sha256 }}\n\nbuild:\n  noarch: python\n  number: 1\n  script: \"{{ PYTHON }} -m pip install . --no-deps -vv\"\n\nrequirements:\n  host:\n    - python\n    - pip\n  run:\n    - python\n    - doct\n    - jsonschema\n    - mongoquery\n    - pymongo\n    - pyyaml\n    - requests\n    - tornado\n    - ujson\n\ntest:\n  imports:\n    - amostra\n    - amostra.client\n    - amostra.sample_data\n    - amostra.server\n    - amostra.test\n\nabout:\n  home: https://nsls-ii.github.io/amostra\n  license: BSD 3-Clause\n  license_file: LICENSE\n  summary: \"amostra is a collection of light-weight sample management classes\"\n",
 "req":{
  "__set__":true,
  "elements":[
   "doct",
   "jsonschema",
   "mongoquery",
   "pip",
   "pymongo",
   "python",
   "pyyaml",
   "requests",
   "tornado",
   "ujson"
  ]
 },
 "requirements":{
  "build":{
   "__set__":true,
   "elements":[]
  },
  "host":{
   "__set__":true,
   "elements":[
    "pip",
    "python"
   ]
  },
  "run":{
   "__set__":true,
   "elements":[
    "doct",
    "jsonschema",
    "mongoquery",
    "pymongo",
    "python",
    "pyyaml",
    "requests",
    "tornado",
    "ujson"
   ]
  },
  "test":{
   "__set__":true,
   "elements":[]
  }
 },
 "strong_exports":false,
 "total_requirements":{
  "build":{
   "__set__":true,
   "elements":[]
  },
  "host":{
   "__set__":true,
   "elements":[
    "pip",
    "python"
   ]
  },
  "run":{
   "__set__":true,
   "elements":[
    "doct",
    "jsonschema",
    "mongoquery",
    "pymongo",
    "python",
    "pyyaml",
    "requests",
    "tornado",
    "ujson"
   ]
  },
  "test":{
   "__set__":true,
   "elements":[]
  }
 },
 "url":"https://github.com/NSLS-II/amostra/archive/v1.0.0.tar.gz",
 "version":"1.0.0",
 "win_64_meta_yaml":{
  "about":{
   "home":"https://nsls-ii.github.io/amostra",
   "license":"BSD 3-Clause",
   "license_file":"LICENSE",
   "summary":"amostra is a collection of light-weight sample management classes"
  },
  "build":{
   "noarch":"python",
   "number":"1",
   "script":" -m pip install . --no-deps -vv"
  },
  "package":{
   "name":"amostra",
   "version":"1.0.0"
  },
  "requirements":{
   "host":[
    "python",
    "pip"
   ],
   "run":[
    "python",
    "doct",
    "jsonschema",
    "mongoquery",
    "pymongo",
    "pyyaml",
    "requests",
    "tornado",
    "ujson"
   ]
  },
  "source":{
   "sha256":"52a34cf993ddc1367832f263b417eb4ed4f88214792acf86a4bd98c6cd5c3173",
   "url":"https://github.com/NSLS-II/amostra/archive/v1.0.0.tar.gz"
  },
  "test":{
   "imports":[
    "amostra",
    "amostra.client",
    "amostra.sample_data",
    "amostra.server",
    "amostra.test"
   ]
  }
 },
 "win_64_requirements":{
  "build":{
   "__set__":true,
   "elements":[]
  },
  "host":{
   "__set__":true,
   "elements":[
    "pip",
    "python"
   ]
  },
  "run":{
   "__set__":true,
   "elements":[
    "doct",
    "jsonschema",
    "mongoquery",
    "pymongo",
    "python",
    "pyyaml",
    "requests",
    "tornado",
    "ujson"
   ]
  },
  "test":{
   "__set__":true,
   "elements":[]
  }
 }
}