{
 "PRed":[
  {
   "PR":{
    "__lazy_json__":"pr_json/470904811.json"
   },
   "data":{
    "bot_rerun":false,
    "migrator_name":"Version",
    "migrator_version":0,
    "version":"0.2.0"
   },
   "keys":[
    "bot_rerun",
    "migrator_name",
    "migrator_version",
    "version"
   ]
  }
 ],
 "bad":false,
 "conda-forge.yml":{
  "provider":{
   "linux":"azure",
   "osx":"azure",
   "win":"azure"
  }
 },
 "feedstock_name":"qtmodern",
 "hash_type":"sha256",
 "linux_64_meta_yaml":{
  "about":{
   "home":"https://www.github.com/gmarull/qtmodern",
   "license":"MIT",
   "license_family":"MIT",
   "license_file":"LICENSE",
   "summary":"Qt Widgets Modern User Interface"
  },
  "build":{
   "noarch":"python",
   "number":"0",
   "script":" -m pip install . --no-deps -vv "
  },
  "package":{
   "name":"qtmodern",
   "version":"0.2.0"
  },
  "requirements":{
   "host":[
    "python >=3.6",
    "pip"
   ],
   "run":[
    "python >=3.6",
    "qtpy >=1.3.1",
    "pyqt >=5"
   ]
  },
  "source":{
   "sha256":"d433a54fbb400d49790aff65d35f203de2a8cc67795ac5bb04c5e766433fafae",
   "url":"https://pypi.io/packages/source/q/qtmodern/qtmodern-0.2.0.tar.gz"
  },
  "test":{
   "imports":[
    "qtmodern",
    "qtmodern.styles",
    "qtmodern.windows"
   ]
  }
 },
 "linux_64_requirements":{
  "build":{
   "__set__":true,
   "elements":[]
  },
  "host":{
   "__set__":true,
   "elements":[
    "pip",
    "python"
   ]
  },
  "run":{
   "__set__":true,
   "elements":[
    "pyqt",
    "python",
    "qtpy"
   ]
  },
  "test":{
   "__set__":true,
   "elements":[]
  }
 },
 "meta_yaml":{
  "about":{
   "home":"https://www.github.com/gmarull/qtmodern",
   "license":"MIT",
   "license_family":"MIT",
   "license_file":"LICENSE",
   "summary":"Qt Widgets Modern User Interface"
  },
  "build":{
   "noarch":"python",
   "number":"0",
   "script":" -m pip install . --no-deps -vv "
  },
  "package":{
   "name":"qtmodern",
   "version":"0.2.0"
  },
  "requirements":{
   "host":[
    "python >=3.6",
    "pip",
    "python >=3.6",
    "pip",
    "python >=3.6",
    "pip"
   ],
   "run":[
    "python >=3.6",
    "qtpy >=1.3.1",
    "pyqt >=5",
    "python >=3.6",
    "qtpy >=1.3.1",
    "pyqt >=5",
    "python >=3.6",
    "qtpy >=1.3.1",
    "pyqt >=5"
   ]
  },
  "source":{
   "sha256":"d433a54fbb400d49790aff65d35f203de2a8cc67795ac5bb04c5e766433fafae",
   "url":"https://pypi.io/packages/source/q/qtmodern/qtmodern-0.2.0.tar.gz"
  },
  "test":{
   "imports":[
    "qtmodern",
    "qtmodern.styles",
    "qtmodern.windows",
    "qtmodern",
    "qtmodern.styles",
    "qtmodern.windows",
    "qtmodern",
    "qtmodern.styles",
    "qtmodern.windows"
   ]
  }
 },
 "name":"qtmodern",
 "new_version":"0.2.0",
 "new_version_attempts":{
  "0.2.0":1
 },
 "new_version_errors":{},
 "osx_64_meta_yaml":{
  "about":{
   "home":"https://www.github.com/gmarull/qtmodern",
   "license":"MIT",
   "license_family":"MIT",
   "license_file":"LICENSE",
   "summary":"Qt Widgets Modern User Interface"
  },
  "build":{
   "noarch":"python",
   "number":"0",
   "script":" -m pip install . --no-deps -vv "
  },
  "package":{
   "name":"qtmodern",
   "version":"0.2.0"
  },
  "requirements":{
   "host":[
    "python >=3.6",
    "pip"
   ],
   "run":[
    "python >=3.6",
    "qtpy >=1.3.1",
    "pyqt >=5"
   ]
  },
  "source":{
   "sha256":"d433a54fbb400d49790aff65d35f203de2a8cc67795ac5bb04c5e766433fafae",
   "url":"https://pypi.io/packages/source/q/qtmodern/qtmodern-0.2.0.tar.gz"
  },
  "test":{
   "imports":[
    "qtmodern",
    "qtmodern.styles",
    "qtmodern.windows"
   ]
  }
 },
 "osx_64_requirements":{
  "build":{
   "__set__":true,
   "elements":[]
  },
  "host":{
   "__set__":true,
   "elements":[
    "pip",
    "python"
   ]
  },
  "run":{
   "__set__":true,
   "elements":[
    "pyqt",
    "python",
    "qtpy"
   ]
  },
  "test":{
   "__set__":true,
   "elements":[]
  }
 },
 "pinning_version":"2020.08.17.20.01.55",
 "raw_meta_yaml":"{% set name = \"qtmodern\" %}\n{% set version = \"0.2.0\" %}\n{% set sha256 = \"d433a54fbb400d49790aff65d35f203de2a8cc67795ac5bb04c5e766433fafae\" %}\n\npackage:\n  name: {{ name|lower }}\n  version: {{ version }}\n\nsource:\n  url: https://pypi.io/packages/source/{{ name[0] }}/{{ name }}/{{ name }}-{{ version }}.tar.gz\n  sha256: {{ sha256 }}\n\nbuild:\n  number: 0\n  noarch: python\n  script: '{{ PYTHON }} -m pip install . --no-deps -vv '\n\nrequirements:\n  host:\n    - python >=3.6\n    - pip\n  run:\n    - python >=3.6\n    - qtpy >=1.3.1\n    - pyqt >=5\n\ntest:\n  imports:\n    - qtmodern\n    - qtmodern.styles\n    - qtmodern.windows\n\nabout:\n  home: https://www.github.com/gmarull/qtmodern\n  license: MIT\n  license_family: MIT\n  license_file: LICENSE\n  summary: Qt Widgets Modern User Interface\n",
 "req":{
  "__set__":true,
  "elements":[
   "pip",
   "pyqt",
   "python",
   "qtpy"
  ]
 },
 "requirements":{
  "build":{
   "__set__":true,
   "elements":[]
  },
  "host":{
   "__set__":true,
   "elements":[
    "pip",
    "python"
   ]
  },
  "run":{
   "__set__":true,
   "elements":[
    "pyqt",
    "python",
    "qtpy"
   ]
  },
  "test":{
   "__set__":true,
   "elements":[]
  }
 },
 "smithy_version":"No azure token. Create a token and\nput it in ~/.conda-smithy/azure.token\n3.7.10",
 "strong_exports":false,
 "total_requirements":{
  "build":{
   "__set__":true,
   "elements":[]
  },
  "host":{
   "__set__":true,
   "elements":[
    "pip",
    "python >=3.6"
   ]
  },
  "run":{
   "__set__":true,
   "elements":[
    "pyqt >=5",
    "python >=3.6",
    "qtpy >=1.3.1"
   ]
  },
  "test":{
   "__set__":true,
   "elements":[]
  }
 },
 "url":"https://pypi.io/packages/source/q/qtmodern/qtmodern-0.1.4.tar.gz",
 "version":"0.2.0",
 "win_64_meta_yaml":{
  "about":{
   "home":"https://www.github.com/gmarull/qtmodern",
   "license":"MIT",
   "license_family":"MIT",
   "license_file":"LICENSE",
   "summary":"Qt Widgets Modern User Interface"
  },
  "build":{
   "noarch":"python",
   "number":"0",
   "script":" -m pip install . --no-deps -vv "
  },
  "package":{
   "name":"qtmodern",
   "version":"0.2.0"
  },
  "requirements":{
   "host":[
    "python >=3.6",
    "pip"
   ],
   "run":[
    "python >=3.6",
    "qtpy >=1.3.1",
    "pyqt >=5"
   ]
  },
  "source":{
   "sha256":"d433a54fbb400d49790aff65d35f203de2a8cc67795ac5bb04c5e766433fafae",
   "url":"https://pypi.io/packages/source/q/qtmodern/qtmodern-0.2.0.tar.gz"
  },
  "test":{
   "imports":[
    "qtmodern",
    "qtmodern.styles",
    "qtmodern.windows"
   ]
  }
 },
 "win_64_requirements":{
  "build":{
   "__set__":true,
   "elements":[]
  },
  "host":{
   "__set__":true,
   "elements":[
    "pip",
    "python"
   ]
  },
  "run":{
   "__set__":true,
   "elements":[
    "pyqt",
    "python",
    "qtpy"
   ]
  },
  "test":{
   "__set__":true,
   "elements":[]
  }
 }
}